CHANGES.rst
CONTRIBUTORS.rst
LICENSE
MANIFEST.in
README.rst
setup.cfg
setup.py
areplay/__init__.py
areplay/main.py
areplay.egg-info/PKG-INFO
areplay.egg-info/SOURCES.txt
areplay.egg-info/dependency_links.txt
areplay.egg-info/entry_points.txt
areplay.egg-info/requires.txt
areplay.egg-info/top_level.txt