Metadata-Version: 1.1
Name: areplay
Version: 0.5
Summary: Apache Log live replicator
Home-page: https://github.com/ssynchron/areplay
Author: Hugo Dias
Author-email: hdias@synchlabs.com
License: UNKNOWN
Download-URL: https://github.com/ssynchron/areplay/tarball/0.5
Keywords: testing,logging
Platform: UNKNOWN
Classifier: Programming Language :: Python
Classifier: License :: OSI Approved :: MIT License
Classifier: Development Status :: 1 - Planning
